{"ids_to_process":{"json":[{"id":"40202"},{"id":"40208"},{"id":"40209"},{"id":"40064"},{"id":"40212"},{"id":"40210"},{"id":"40163"},{"id":"40207"},{"id":"40211"},{"id":"40205"},{"id":"40204"},{"id":"39964"},{"id":"39963"},{"id":"39962"},{"id":"39961"},{"id":"39959"},{"id":"39958"},{"id":"39955"},{"id":"39952"},{"id":"39951"}],"db":[{"id":"40202"},{"id":"40208"},{"id":"40209"},{"id":"40064"},{"id":"40212"},{"id":"40210"},{"id":"40163"},{"id":"40207"},{"id":"40211"},{"id":"40205"},{"id":"40204"},{"id":"39964"},{"id":"39963"},{"id":"39962"},{"id":"39961"},{"id":"39959"},{"id":"39958"},{"id":"39955"},{"id":"39952"},{"id":"39951"}]}}