{"ids_to_process":{"json":[{"id":"39725"},{"id":"39746"},{"id":"39749"},{"id":"39752"},{"id":"39736"},{"id":"39735"},{"id":"39732"},{"id":"39747"},{"id":"39744"},{"id":"39745"},{"id":"39741"},{"id":"39743"},{"id":"39699"},{"id":"39740"},{"id":"39742"},{"id":"39712"},{"id":"39737"},{"id":"39738"},{"id":"39739"},{"id":"39694"},{"id":"39693"}],"db":[{"id":"39725"},{"id":"39746"},{"id":"39749"},{"id":"39752"},{"id":"39736"},{"id":"39735"},{"id":"39732"},{"id":"39747"},{"id":"39744"},{"id":"39745"},{"id":"39741"},{"id":"39743"},{"id":"39699"},{"id":"39740"},{"id":"39742"},{"id":"39712"},{"id":"39737"},{"id":"39738"},{"id":"39739"},{"id":"39694"},{"id":"39693"}]}}