{"ids_to_process":{"json":[{"id":"44229?active=1"},{"id":"44230?active=1"},{"id":"44228?active=1"},{"id":"44226?active=1"},{"id":"44194?active=1"},{"id":"44224?active=1"},{"id":"44191?active=1"},{"id":"44225?active=1"},{"id":"44190?active=1"},{"id":"44189?active=1"},{"id":"44132?active=1"},{"id":"44168?active=1"},{"id":"44169?active=1"},{"id":"44199?active=1"},{"id":"44218?active=1"},{"id":"44201?active=1"},{"id":"44220?active=1"},{"id":"44219?active=1"},{"id":"44059?active=1"},{"id":"44214?active=1"},{"id":"44070?active=1"},{"id":"44057?active=1"},{"id":"44066?active=1"},{"id":"44068?active=1"},{"id":"44177?active=1"},{"id":"44179?active=1"},{"id":"44195?active=1"},{"id":"44188?active=1"},{"id":"44200?active=1"},{"id":"44202?active=1"},{"id":"44158?active=1"},{"id":"44193?active=1"},{"id":"44192?active=1"},{"id":"44187?active=1"},{"id":"44182?active=1"},{"id":"44183?active=1"},{"id":"44184?active=1"},{"id":"44162?active=1"},{"id":"44178?active=1"},{"id":"44139?active=1"},{"id":"44180?active=1"},{"id":"44181?active=1"},{"id":"44085?active=1"},{"id":"44160?active=1"},{"id":"44161?active=1"},{"id":"44044?active=1"},{"id":"44045?active=1"},{"id":"44152?active=1"},{"id":"44153?active=1"},{"id":"44154?active=1"}],"db":[{"id":"44229?active=1"},{"id":"44230?active=1"},{"id":"44228?active=1"},{"id":"44226?active=1"},{"id":"44194?active=1"},{"id":"44224?active=1"},{"id":"44191?active=1"},{"id":"44225?active=1"},{"id":"44190?active=1"},{"id":"44189?active=1"},{"id":"44132?active=1"},{"id":"44168?active=1"},{"id":"44169?active=1"},{"id":"44199?active=1"},{"id":"44218?active=1"},{"id":"44201?active=1"},{"id":"44220?active=1"},{"id":"44219?active=1"},{"id":"44059?active=1"},{"id":"44214?active=1"},{"id":"44070?active=1"},{"id":"44057?active=1"},{"id":"44066?active=1"},{"id":"44068?active=1"},{"id":"44177?active=1"},{"id":"44179?active=1"},{"id":"44195?active=1"},{"id":"44188?active=1"},{"id":"44200?active=1"},{"id":"44202?active=1"},{"id":"44158?active=1"},{"id":"44193?active=1"},{"id":"44192?active=1"},{"id":"44187?active=1"},{"id":"44182?active=1"},{"id":"44183?active=1"},{"id":"44184?active=1"},{"id":"44162?active=1"},{"id":"44178?active=1"},{"id":"44139?active=1"},{"id":"44180?active=1"},{"id":"44181?active=1"},{"id":"44085?active=1"},{"id":"44160?active=1"},{"id":"44161?active=1"},{"id":"44044?active=1"},{"id":"44045?active=1"},{"id":"44152?active=1"},{"id":"44153?active=1"},{"id":"44154?active=1"}]}}